fantastic_otter/__init__.py
fantastic_otter/speak.py
fantastic_otter-1.0.0.dev0.dist-info/METADATA
fantastic_otter-1.0.0.dev0.dist-info/WHEEL
fantastic_otter-1.0.0.dev0.dist-info/top_level.txt
fantastic_otter-1.0.0.dev0.dist-info/RECORD
