Metadata-Version: 2.1
Name: fantastic_otter
Version: 1.0.0.dev0
Requires-Python: >=3.11
Requires-Dist: loguru >=0.7.2
